CHANGELOG.txt
LICENCE.txt
MANIFEST.in
README.txt
agent.py
setup.py
ThinkDashboardAgent/__init__.py
ThinkDashboardAgent/helpers/__init__.py
ThinkDashboardAgent/helpers/get_data.py
ThinkDashboardAgent/helpers/put_data.py
ThinkDashboardAgent/main/__init__.py
ThinkDashboardAgent/main/base.py
ThinkDashboardAgent/main/load_config.py
ThinkDashboardAgent/main/settings.py
ThinkDashboardAgent/providers/__init__.py
ThinkDashboardAgent/providers/database_provider.py
ThinkDashboardAgent/providers/elasticsearch_provider.py
ThinkDashboardAgent/providers/redis_provider.py
ThinkDashboardAgent/providers/site_provider.py
ThinkDashboardAgent/providers/ssl_provider.py
think_agent_01.egg-info/PKG-INFO
think_agent_01.egg-info/SOURCES.txt
think_agent_01.egg-info/dependency_links.txt
think_agent_01.egg-info/requires.txt
think_agent_01.egg-info/top_level.txt